jupyterlab_gruvbox_dark/__init__.py
jupyterlab_gruvbox_dark/_version.py
jupyterlab_gruvbox_dark/labextension/package.json
jupyterlab_gruvbox_dark/labextension/static/568.97e9e0210be7c1c3cf16.js
jupyterlab_gruvbox_dark/labextension/static/remoteEntry.67f0104cdc8c7d4ac5af.js
jupyterlab_gruvbox_dark/labextension/static/style.js
jupyterlab_gruvbox_dark/labextension/static/third-party-licenses.json
jupyterlab_gruvbox_dark/labextension/themes/jupyterlab_gruvbox_dark/index.css
jupyterlab_gruvbox_dark/labextension/themes/jupyterlab_gruvbox_dark/index.js
jupyterlab_gruvbox_dark-0.1.0.data/data/share/jupyter/labextensions/jupyterlab_gruvbox_dark/install.json
jupyterlab_gruvbox_dark-0.1.0.data/data/share/jupyter/labextensions/jupyterlab_gruvbox_dark/package.json
jupyterlab_gruvbox_dark-0.1.0.data/data/share/jupyter/labextensions/jupyterlab_gruvbox_dark/static/568.97e9e0210be7c1c3cf16.js
jupyterlab_gruvbox_dark-0.1.0.data/data/share/jupyter/labextensions/jupyterlab_gruvbox_dark/static/remoteEntry.67f0104cdc8c7d4ac5af.js
jupyterlab_gruvbox_dark-0.1.0.data/data/share/jupyter/labextensions/jupyterlab_gruvbox_dark/static/style.js
jupyterlab_gruvbox_dark-0.1.0.data/data/share/jupyter/labextensions/jupyterlab_gruvbox_dark/static/third-party-licenses.json
jupyterlab_gruvbox_dark-0.1.0.data/data/share/jupyter/labextensions/jupyterlab_gruvbox_dark/themes/jupyterlab_gruvbox_dark/index.css
jupyterlab_gruvbox_dark-0.1.0.data/data/share/jupyter/labextensions/jupyterlab_gruvbox_dark/themes/jupyterlab_gruvbox_dark/index.js
jupyterlab_gruvbox_dark-0.1.0.dist-info/LICENSE
jupyterlab_gruvbox_dark-0.1.0.dist-info/METADATA
jupyterlab_gruvbox_dark-0.1.0.dist-info/WHEEL
jupyterlab_gruvbox_dark-0.1.0.dist-info/top_level.txt
jupyterlab_gruvbox_dark-0.1.0.dist-info/RECORD
